justdays/__init__.py
justdays/day.py
justdays/period.py
justdays-1.9.3.dist-info/LICENSE
justdays-1.9.3.dist-info/METADATA
justdays-1.9.3.dist-info/WHEEL
justdays-1.9.3.dist-info/top_level.txt
justdays-1.9.3.dist-info/RECORD
