Metadata-Version: 2.1
Name: justdays
Version: 1.9.3
Summary: Makes working with days super easy
Author-email: HP Harmsen <hp@harmsen.nl>
License: This is free and unencumbered software released into the public domain.
Project-URL: Homepage, https://github.com/hpharmsen/justdays
Keywords: days,adding days,difference between days,range of days,last Monday
Classifier: Programming Language :: Python
Classifier: Programming Language :: Python :: 3
Requires-Python: >=3.7
License-File: LICENSE
Requires-Dist: python-dateutil
Provides-Extra: dev
Requires-Dist: black ; extra == 'dev'
Requires-Dist: pytest ; extra == 'dev'
Requires-Dist: build ; extra == 'dev'
Requires-Dist: twine ; extra == 'dev'
Requires-Dist: nox ; extra == 'dev'
